liqueur/__init__.py
liqueur/app.py
liqueur/center.py
liqueur/channel.py
liqueur/codes.py
liqueur/config.py
liqueur/dll.py
liqueur/quote.py
liqueur/reply.py
liqueur/sqlalchemy.py
liqueur/structure.py
liqueur/util.py
liqueur/tests/__init__.py
liqueur/tests/test_helper.py
liqueur-0.0.5.dist-info/LICENSE
liqueur-0.0.5.dist-info/METADATA
liqueur-0.0.5.dist-info/WHEEL
liqueur-0.0.5.dist-info/top_level.txt
liqueur-0.0.5.dist-info/RECORD
